jl_ecms_server-0.45.0.dist-info/licenses/LICENSE
mirix/__init__.py
mirix/__main__.py
mirix/config.py
mirix/constants.py
mirix/embeddings.py
mirix/errors.py
mirix/interface.py
mirix/log.py
mirix/memory.py
mirix/sdk.py
mirix/settings.py
mirix/system.py
mirix/tracing.py
mirix/utils.py
mirix/voice_utils.py
mirix/agent/__init__.py
mirix/agent/agent.py
mirix/agent/agent_configs.py
mirix/agent/agent_states.py
mirix/agent/app_constants.py
mirix/agent/app_utils.py
mirix/agent/background_agent.py
mirix/agent/core_memory_agent.py
mirix/agent/episodic_memory_agent.py
mirix/agent/knowledge_vault_memory_agent.py
mirix/agent/message_queue.py
mirix/agent/meta_agent.py
mirix/agent/meta_memory_agent.py
mirix/agent/procedural_memory_agent.py
mirix/agent/reflexion_agent.py
mirix/agent/resource_memory_agent.py
mirix/agent/semantic_memory_agent.py
mirix/agent/temporary_message_accumulator.py
mirix/agent/tool_validators.py
mirix/agent/upload_manager.py
mirix/client/__init__.py
mirix/client/client.py
mirix/client/remote_client.py
mirix/client/utils.py
mirix/configs/__init__.py
mirix/configs/mirix.yaml
mirix/configs/examples/mirix_azure.yaml
mirix/configs/examples/mirix_claude.yaml
mirix/configs/examples/mirix_gemini.yaml
mirix/configs/examples/mirix_openai.yaml
mirix/configs/legacy_configs/mirix.yaml
mirix/configs/legacy_configs/mirix_azure_example.yaml
mirix/configs/legacy_configs/mirix_custom_model.yaml
mirix/configs/legacy_configs/mirix_custom_prompts.yaml
mirix/configs/legacy_configs/mirix_gemini.yaml
mirix/configs/legacy_configs/mirix_gpt4.yaml
mirix/configs/legacy_configs/mirix_gpt4o-mini.yaml
mirix/configs/legacy_configs/mirix_monitor.yaml
mirix/database/__init__.py
mirix/database/pglite_connector.py
mirix/database/redis_client.py
mirix/database/schema_extractor.py
mirix/functions/__init__.py
mirix/functions/ast_parsers.py
mirix/functions/functions.py
mirix/functions/helpers.py
mirix/functions/schema_generator.py
mirix/functions/function_sets/__init__.py
mirix/functions/function_sets/base.py
jl_ecms_server-0.45.0.dist-info/METADATA
jl_ecms_server-0.45.0.dist-info/WHEEL
jl_ecms_server-0.45.0.dist-info/entry_points.txt
jl_ecms_server-0.45.0.dist-info/top_level.txt
jl_ecms_server-0.45.0.dist-info/RECORD
