Metadata-Version: 2.4
Name: jl-ecms-server
Version: 0.45.0
Summary: MIRIX Server - Multi-Agent Personal Assistant with Advanced Memory System
Home-page: https://github.com/Mirix-AI/MIRIX
Author: Mirix AI
Author-email: yuwang@mirix.io
License: Apache License 2.0
Project-URL: Documentation, https://docs.mirix.io
Project-URL: Website, https://mirix.io
Project-URL: Source Code, https://github.com/Mirix-AI/MIRIX
Project-URL: Bug Reports, https://github.com/Mirix-AI/MIRIX/issues
Keywords: ai,memory,agent,llm,assistant,chatbot,multimodal,server,fastapi
Classifier: Development Status :: 4 - Beta
Classifier: Intended Audience :: Developers
Classifier: License :: OSI Approved :: Apache Software License
Classifier: Operating System :: OS Independent
Classifier: Programming Language :: Python :: 3
Classifier: Programming Language :: Python :: 3.10
Classifier: Programming Language :: Python :: 3.11
Classifier: Programming Language :: Python :: 3.12
Classifier: Programming Language :: Python :: 3.13
Classifier: Topic :: Scientific/Engineering :: Artificial Intelligence
Classifier: Topic :: Software Development :: Libraries :: Python Modules
Classifier: Topic :: Communications :: Chat
Classifier: Framework :: FastAPI
Requires-Python: >=3.10
License-File: LICENSE
Requires-Dist: pytz>=2024.1
Requires-Dist: numpy>=1.24.0
Requires-Dist: pandas>=2.0.0
Requires-Dist: openpyxl>=3.1.0
Requires-Dist: Markdown>=3.5.0
Requires-Dist: Pillow<11.0.0,>=10.2.0
Requires-Dist: scikit-image>=0.22.0
Requires-Dist: openai<2.0.0,>=1.108.1
Requires-Dist: tiktoken>=0.5.0
Requires-Dist: google-genai>=0.4.0
Requires-Dist: anthropic>=0.23.0
Requires-Dist: cohere>=4.0.0
Requires-Dist: fastapi>=0.104.1
Requires-Dist: uvicorn[standard]>=0.31.1
Requires-Dist: python-multipart>=0.0.6
Requires-Dist: httpx>=0.25.0
Requires-Dist: httpx_sse>=0.3.0
Requires-Dist: sqlalchemy>=2.0.0
Requires-Dist: psycopg2-binary>=2.9.0
Requires-Dist: pg8000>=1.30.0
Requires-Dist: pgvector>=0.2.0
Requires-Dist: redis>=5.0.0
Requires-Dist: pydantic>=2.0.0
Requires-Dist: pydantic-settings>=2.0.0
Requires-Dist: python-dotenv>=1.0.0
Requires-Dist: demjson3>=3.0.0
Requires-Dist: pathvalidate>=3.0.0
Requires-Dist: docstring_parser>=0.15
Requires-Dist: jinja2>=3.1.0
Requires-Dist: humps>=0.2.0
Requires-Dist: colorama>=0.4.0
Requires-Dist: rapidfuzz>=3.0.0
Requires-Dist: rank-bm25>=0.2.0
Requires-Dist: psutil>=5.9.0
Requires-Dist: json_repair>=0.12.0
Requires-Dist: rich<14.0.0,>=13.7.1
Requires-Dist: anyio>=4.7.0
Requires-Dist: pyyaml>=6.0.0
Requires-Dist: requests>=2.31.0
Requires-Dist: llama_index>=0.9.0
Requires-Dist: llama-index-embeddings-google-genai>=0.1.0
Requires-Dist: composio>=0.3.0
Requires-Dist: mcp>=0.1.0
Requires-Dist: google-auth>=2.0.0
Requires-Dist: google-auth-oauthlib>=1.0.0
Requires-Dist: google-auth-httplib2>=0.1.0
Requires-Dist: google-api-python-client>=2.0.0
Requires-Dist: opentelemetry-api>=1.20.0
Requires-Dist: opentelemetry-sdk>=1.20.0
Requires-Dist: opentelemetry-exporter-otlp>=1.20.0
Requires-Dist: opentelemetry-instrumentation-requests>=0.41b0
Requires-Dist: langfuse<4.0.0,>=3.11.0
Requires-Dist: SpeechRecognition>=3.10.0
Requires-Dist: pydub>=0.25.0
Requires-Dist: protobuf<6.0.0,>=5.0.0
Provides-Extra: dev
Requires-Dist: pytest>=6.0.0; extra == "dev"
Requires-Dist: pytest-asyncio>=0.21.0; extra == "dev"
Requires-Dist: pytest-cov>=4.0.0; extra == "dev"
Requires-Dist: black>=23.0.0; extra == "dev"
Requires-Dist: isort>=5.12.0; extra == "dev"
Requires-Dist: flake8>=6.0.0; extra == "dev"
Requires-Dist: mypy>=1.5.0; extra == "dev"
Requires-Dist: ruff>=0.1.0; extra == "dev"
Requires-Dist: pyright>=1.1.0; extra == "dev"
Dynamic: author
Dynamic: author-email
Dynamic: classifier
Dynamic: description
Dynamic: description-content-type
Dynamic: home-page
Dynamic: keywords
Dynamic: license
Dynamic: license-file
Dynamic: project-url
Dynamic: provides-extra
Dynamic: requires-dist
Dynamic: requires-python
Dynamic: summary
